letterer/__init__.py
letterer-0.0.2.dist-info/LICENCE
letterer-0.0.2.dist-info/METADATA
letterer-0.0.2.dist-info/WHEEL
letterer-0.0.2.dist-info/top_level.txt
letterer-0.0.2.dist-info/RECORD
