Metadata-Version: 2.1
Name: letterer
Version: 0.0.2
Summary: More string methods.
Home-page: https://github.com/mathstar13/letterer
Author: greatusername
Author-email: alexander.destefano@gmail.com
License: UNKNOWN
Platform: UNKNOWN
Classifier: Programming Language :: Python :: 3
Classifier: License :: OSI Approved :: MIT License
Classifier: Operating System :: OS Independent
Requires-Python: >=2.5
License-File: LICENCE
